{
  "created_at_utc": "2026-05-07T06:23:08.438886+00:00",
  "raw_prices_path": "data/raw_prices/all_daily_prices.csv",
  "universe_path": "data/sp500_top80_universe.csv",
  "download_log_path": "data/raw_prices/download_log.csv",
  "price_column": "AdjClose",
  "start_date": "2015-01-01",
  "end_date": "2024-12-31",
  "initial_universe_asset_count": 80,
  "download_success_asset_count": 79,
  "download_failed_asset_count": 1,
  "downloaded_price_asset_count": 79,
  "cleaned_asset_count": 76,
  "dropped_asset_count": 3,
  "common_calendar_days": 2516,
  "raw_price_rows": 193414,
  "duplicate_rows_after_basic_load": 0,
  "cleaned_return_days": 2514,
  "calendar_min_asset_ratio": 0.8,
  "max_price_missing_ratio": 0.05,
  "max_first_valid_lag_days": 31,
  "max_last_valid_lag_days": 10,
  "max_consecutive_missing_days": 5,
  "ffill_limit": 2,
  "hard_return_cap": 0.5,
  "hard_outlier_count": 1,
  "winsor_lower": 0.001,
  "winsor_upper": 0.999,
  "winsor_clipped_count": 456,
  "rows_before_missing_drop": 2515,
  "missing_cells_before_final_drop": 1,
  "rows_dropped_due_to_missing_returns": 1,
  "final_returns_have_missing": false,
  "cleaned_returns_path": "data\\cleaned\\cleaned_returns.csv",
  "cleaned_prices_path": "data\\cleaned\\cleaned_adjclose_prices.csv",
  "asset_diagnostics_path": "data\\cleaned\\asset_cleaning_diagnostics.csv",
  "outlier_report_path": "data\\cleaned\\outlier_report.csv",
  "calendar_coverage_path": "data\\cleaned\\calendar_coverage.csv",
  "cleaning_summary_path": "data\\cleaned\\cleaning_summary.json",
  "report_path": "data\\cleaned\\data_cleaning_report.md"
}